gfosd/__init__.py
gfosd/data_generators.py
gfosd/problem.py
gfosd/components/__init__.py
gfosd/components/aggregate.py
gfosd/components/base_graph_class.py
gfosd/components/basis_constraints.py
gfosd/components/equality_constraints.py
gfosd/components/finite_set.py
gfosd/components/inequality_constraints.py
gfosd/components/sums.py
gfosd/components/utilities.py
osd/__init__.py
osd/generators.py
osd/masking.py
osd/polish.py
osd/problem.py
osd/signal_decomp_admm.py
osd/signal_decomp_bcd.py
osd/utilities.py
osd/validation.py
osd/classes/__init__.py
osd/classes/approx_periodic.py
osd/classes/asymmetric_noise.py
osd/classes/base_graph_class.py
osd/classes/blank.py
osd/classes/boolean.py
osd/classes/component.py
osd/classes/constant.py
osd/classes/frozen.py
osd/classes/linear_trend.py
osd/classes/markov.py
osd/classes/mean_square_small.py
osd/classes/norm1_first.py
osd/classes/norm1_second.py
osd/classes/one_jump.py
osd/classes/piecewise_constant.py
osd/classes/quad_lin.py
osd/classes/quadlin_utilities.py
osd/classes/smooth_first.py
osd/classes/smooth_second.py
osd/classes/sparse.py
osd/classes/time_smooth_entry_close.py
osd/classes/wrappers.py
osd/classes/C/__init__.py
osd/classes/C/make_l1_trend_module.py
osd/classes/C/l1_tf/COPYING.TXT
osd/classes/C/l1_tf/Makefile
osd/classes/C/l1_tf/Makefile.solaris
osd/classes/C/l1_tf/README.TXT
osd/classes/C/l1_tf/blas.h
osd/classes/C/l1_tf/l1tf
osd/classes/C/l1_tf/l1tf.c
osd/classes/C/l1_tf/l1tf.h
osd/classes/C/l1_tf/lapack.h
osd/classes/C/l1_tf/main.c
osd/classes/C/l1_tf/make.sh
osd/classes/C/l1_tf/result.txt
osd/classes/C/l1_tf/snp500.txt
sig_decomp-0.3.2.dist-info/LICENSE
sig_decomp-0.3.2.dist-info/METADATA
sig_decomp-0.3.2.dist-info/WHEEL
sig_decomp-0.3.2.dist-info/top_level.txt
sig_decomp-0.3.2.dist-info/RECORD
