Metadata-Version: 2.1
Name: sig-decomp
Version: 0.3.2
Summary: Optimization-based signal decomposition
Author-email: Bennet Meyers <bennetm@stanford.edu>
Maintainer-email: Sara Miskovich <smiskov@slac.stanford.edu>
License: BSD 3-Clause License
Project-URL: Homepage, https://github.com/cvxgrp/signal-decomposition
Project-URL: Bug Tracker, https://github.com/cvxgrp/signal-decomposition/issues
Keywords: convex optimization,optimization
Classifier: Development Status :: 4 - Beta
Classifier: License :: OSI Approved :: BSD License
Classifier: Programming Language :: Python :: 3 :: Only
Classifier: Programming Language :: Python :: 3.6
Classifier: Programming Language :: Python :: 3.7
Classifier: Programming Language :: Python :: 3.8
Classifier: Programming Language :: Python :: 3.9
Classifier: Programming Language :: Python :: 3.10
Classifier: Programming Language :: Python :: 3.11
Classifier: Programming Language :: Python :: 3.12
Classifier: Intended Audience :: Science/Research
Classifier: Topic :: Scientific/Engineering
Requires-Python: >=3.6
License-File: LICENSE
Requires-Dist: cvxpy
Requires-Dist: matplotlib
Requires-Dist: numpy
Requires-Dist: scipy
Requires-Dist: scikit-learn
Requires-Dist: qss
Requires-Dist: pandas
